dissert/__init__.py
dissert/dissert.py
dissert-1.0.dist-info/METADATA
dissert-1.0.dist-info/WHEEL
dissert-1.0.dist-info/top_level.txt
dissert-1.0.dist-info/zip-safe
dissert-1.0.dist-info/RECORD
