Metadata-Version: 2.1
Name: dissert
Version: 1.0
Summary: Granular assertion-disabling via content encodings
Home-page: https://github.com/boothby/dissert
Author: Kelly Boothby
Author-email: UNKNOWN
License: MIT
Platform: UNKNOWN
Requires-Dist: unparse
